localfunk
test
