Metadata-Version: 2.1
Name: localfunk
Version: 0.0.2
Summary: Proxy Lambda functions to local code
Home-page: https://github.com/atomraymaker/localfunk
Author: Adam Baker
Author-email: adambaker@keemail.me
License: MIT
Platform: UNKNOWN
Classifier: License :: OSI Approved :: MIT License
Classifier: Programming Language :: Python :: 3
Classifier: Programming Language :: Python :: 3.7
